plinkliftover/__init__.py
plinkliftover/__main__.py
plinkliftover/bed2map.py
plinkliftover/liftover.py
plinkliftover/logger.py
plinkliftover/map2bed.py
plinkliftover/py.typed
plinkliftover-0.5.2.dist-info/METADATA
plinkliftover-0.5.2.dist-info/WHEEL
plinkliftover-0.5.2.dist-info/entry_points.txt
plinkliftover-0.5.2.dist-info/licenses/LICENSE.md
plinkliftover-0.5.2.dist-info/RECORD
