Metadata-Version: 2.1
Name: plinkliftover
Version: 0.5.2
Summary: Converts genotype data stored in plink's PED+MAP format from one genome build to another, using liftOver
Project-URL: repository, https://github.com/milescsmith/plinkliftover
Project-URL: homepage, https://github.com/milescsmith/plinkliftover
Author-email: Miles Smith <miles-smith@omrf.org>
License-File: LICENSE.md
Classifier: Development Status :: 3 - Alpha
Classifier: Intended Audience :: Developers
Classifier: Operating System :: OS Independent
Classifier: Topic :: Software Development :: Libraries :: Python Modules
Requires-Python: >=3.10
Requires-Dist: better-exceptions
Requires-Dist: joblib==1.3.1
Requires-Dist: loguru==0.7.0
Requires-Dist: psutil==5.9.5
Requires-Dist: rich==13.5.2
Requires-Dist: tqdm==4.65.0
Requires-Dist: typer==0.9.0
Provides-Extra: dev
Requires-Dist: black==23.7.0; extra == 'dev'
Requires-Dist: build==0.10.0; extra == 'dev'
Requires-Dist: mypy==1.5.1; extra == 'dev'
Requires-Dist: nox==2023.4.22; extra == 'dev'
Requires-Dist: pytest==7.4.0; extra == 'dev'
Requires-Dist: ruff==0.0.287; extra == 'dev'
